pyside6_modern-0.1.1.dist-info/METADATA
pyside6_modern-0.1.1.dist-info/WHEEL
pyside6_modern-0.1.1.dist-info/entry_points.txt
pyside6_modern-0.1.1.dist-info/licenses/LICENSE
pyside6_modern/__init__.py
pyside6_modern/assets/__init__.py
pyside6_modern/assets/i18n/modern_main_window_en_US.qm
pyside6_modern/assets/i18n/modern_main_window_en_US.ts
pyside6_modern/assets/i18n/modern_main_window_zh_CN.qm
pyside6_modern/assets/i18n/modern_main_window_zh_CN.ts
pyside6_modern/assets/resources.py
pyside6_modern/assets/resources.qrc
pyside6_modern/assets/themes/dracula/icons/cil-3d.png
pyside6_modern/assets/themes/dracula/icons/cil-4k.png
pyside6_modern/assets/themes/dracula/icons/cil-account-logout.png
pyside6_modern/assets/themes/dracula/icons/cil-action-redo.png
pyside6_modern/assets/themes/dracula/icons/cil-action-undo.png
pyside6_modern/assets/themes/dracula/icons/cil-airplane-mode-off.png
pyside6_modern/assets/themes/dracula/icons/cil-airplane-mode.png
pyside6_modern/assets/themes/dracula/icons/cil-alarm.png
pyside6_modern/assets/themes/dracula/icons/cil-align-center.png
pyside6_modern/assets/themes/dracula/icons/cil-align-left.png
pyside6_modern/assets/themes/dracula/icons/cil-align-right.png
pyside6_modern/assets/themes/dracula/icons/cil-arrow-bottom-2.png
pyside6_modern/assets/themes/dracula/icons/cil-arrow-bottom.png
pyside6_modern/assets/themes/dracula/icons/cil-arrow-circle-bottom.png
pyside6_modern/assets/themes/dracula/icons/cil-arrow-circle-left.png
pyside6_modern/assets/themes/dracula/icons/cil-arrow-circle-right.png
pyside6_modern/assets/themes/dracula/icons/cil-arrow-circle-top.png
pyside6_modern/assets/themes/dracula/icons/cil-arrow-left.png
pyside6_modern/assets/themes/dracula/icons/cil-arrow-right.png
pyside6_modern/assets/themes/dracula/icons/cil-arrow-top.png
pyside6_modern/assets/themes/dracula/icons/cil-at.png
pyside6_modern/assets/themes/dracula/icons/cil-av-timer.png
pyside6_modern/assets/themes/dracula/icons/cil-ban.png
pyside6_modern/assets/themes/dracula/icons/cil-battery-0.png
pyside6_modern/assets/themes/dracula/icons/cil-battery-3.png
pyside6_modern/assets/themes/dracula/icons/cil-battery-5.png
pyside6_modern-0.1.1.dist-info/RECORD
