Metadata-Version: 2.1
Name: PySide6-Modern
Version: 0.1.1
Summary: 基于PySide6实现的现代UI框架
Author-Email: =?utf-8?b?5rGf55m95rKz?= <baiheqiuhan@qq.com>
License: GPL-3.0
Requires-Python: <3.12,>=3.8
Requires-Dist: loguru>=0.7.2
Requires-Dist: pydantic==2.9.1
Requires-Dist: pywin32==227
Requires-Dist: PySide6>=6.4.2
